easy_serialize/__init__.py
easy_serialize/py.typed
easy_serialize/serialize.py
easy_serialize-0.0.3.dist-info/LICENSE
easy_serialize-0.0.3.dist-info/METADATA
easy_serialize-0.0.3.dist-info/WHEEL
easy_serialize-0.0.3.dist-info/top_level.txt
easy_serialize-0.0.3.dist-info/RECORD
