Metadata-Version: 2.1
Name: easy-serialize
Version: 0.0.3
Summary: A simple way to turn objects into strings and vice-versa
Home-page: https://github.com/hydrogen602/easy-serialize
Author: Jonathan Rotter
Author-email: hydrogen31415@gmail.com
License: UNKNOWN
Project-URL: Bug Tracker, https://github.com/hydrogen602/easy-serialize/issues
Platform: UNKNOWN
Classifier: Programming Language :: Python :: 3
Classifier: License :: OSI Approved :: MIT License
Classifier: Operating System :: OS Independent
Requires-Python: >=3.6
